<Properties StartupConfiguration="{2739083D-BD6A-EF71-7844-B438E0DFC5F5}|">
  <MonoDevelop.Ide.Workbench>
    <Pads>
      <Pad Id="ProjectPad">
        <State name="__root__">
          <Node name="LaserDefender" expanded="True">
            <Node name="Assets" expanded="True">
              <Node name="Scripts" expanded="True">
                <Node name="Player.cs" selected="True" />
              </Node>
            </Node>
          </Node>
        </State>
      </Pad>
    </Pads>
  </MonoDevelop.Ide.Workbench>
  <MonoDevelop.Ide.DebuggingService.PinnedWatches />
  <MonoDevelop.Ide.Workspace ActiveConfiguration="Debug" />
  <MonoDevelop.Ide.ItemProperties.Assembly-CSharp PreferredExecutionTarget="c1362523-9c5a-49e3-a8dc-2b40104f094e" />
  <MonoDevelop.Ide.DebuggingService.Breakpoints>
    <BreakpointStore />
  </MonoDevelop.Ide.DebuggingService.Breakpoints>
  <MultiItemStartupConfigurations />
</Properties>